readium/__init__.py
readium/__main__.py
readium/cli.py
readium/config.py
readium/core.py
readium/utils/error_handling.py
readium-0.5.2.dist-info/LICENSE
readium-0.5.2.dist-info/METADATA
readium-0.5.2.dist-info/WHEEL
readium-0.5.2.dist-info/entry_points.txt
readium-0.5.2.dist-info/RECORD
