Metadata-Version: 2.3
Name: readium
Version: 0.5.2
Summary: A tool to extract and analyze documentation from repositories, directories, and URLs
License: MIT
Author: Pablo Toledo
Author-email: pablotoledo@users.noreply.github.com
Requires-Python: >=3.10,<4.0
Classifier: Development Status :: 3 - Alpha
Classifier: Environment :: Console
Classifier: Intended Audience :: Developers
Classifier: License :: OSI Approved :: MIT License
Classifier: Operating System :: OS Independent
Classifier: Programming Language :: Python :: 3
Classifier: Programming Language :: Python :: 3.10
Classifier: Programming Language :: Python :: 3.11
Classifier: Programming Language :: Python :: 3.12
Classifier: Topic :: Software Development :: Documentation
Provides-Extra: tokenizers
Requires-Dist: black (>=24.10.0,<25.0.0)
Requires-Dist: click (>=8.1.8,<9.0.0)
Requires-Dist: isort (>=5.12.0,<6.0.0)
Requires-Dist: lxml[html-clean] (>=5.3.1,<6.0.0)
Requires-Dist: markitdown (>=0.0.1a3,<0.0.2)
Requires-Dist: pypdf (>=4.3.1,<5.0.0)
Requires-Dist: rich (>=13.9.4,<14.0.0)
Requires-Dist: tiktoken (>=0.3.1)
Requires-Dist: trafilatura (>=1.6.0,<2.0.0)
Project-URL: Homepage, https://github.com/pablotoledo/readium
Project-URL: Issues, https://github.com/pablotoledo/readium/issues
Project-URL: Repository, https://github.com/pablotoledo/readium.git
